tinypeel/tinypeel.py
tinypeel/Peeling/Peeling.py
tinypeel/Peeling/PeelingIO.py
tinypeel/Peeling/PeelingInfo.py
tinypeel/Peeling/PeelingUpdates.py
tinypeel/tinyhouse/BurrowsWheelerLibrary.py
tinypeel/tinyhouse/CombinedHMM.py
tinypeel/tinyhouse/DiploidHMM.py
tinypeel/tinyhouse/HaploidHMM.py
tinypeel/tinyhouse/HaplotypeLibrary.py
tinypeel/tinyhouse/HaplotypeOperations.py
tinypeel/tinyhouse/InputOutput.py
tinypeel/tinyhouse/MultiThreadIO.py
tinypeel/tinyhouse/NumbaUtils.py
tinypeel/tinyhouse/Pedigree.py
tinypeel/tinyhouse/ProbMath.py
tinypeel/tinyhouse/Utils.py
AlphaPeel-1.1.3.dist-info/METADATA
AlphaPeel-1.1.3.dist-info/WHEEL
AlphaPeel-1.1.3.dist-info/entry_points.txt
AlphaPeel-1.1.3.dist-info/top_level.txt
AlphaPeel-1.1.3.dist-info/RECORD
