Metadata-Version: 2.1
Name: AlphaPeel
Version: 1.1.3
Summary: Multilocus and hybrid peeling
Author: Andrew Whalen
Author-email: Andrew Whalen <awhalen@roslin.ed.ac.uk>
License: Copyright (C) 2020 University of Edinburgh
Project-URL: Homepage, https://github.com/AlphaGenes/AlphaPeel
Project-URL: Bug Tracker, https://github.com/AlphaGenes/AlphaPeel/issues
Classifier: Programming Language :: Python :: 3
Classifier: License :: OSI Approved :: MIT License
Requires-Dist: numpy (>=1.19)
Requires-Dist: numba (>=0.50.0)
